yams_cli/__init__.py
yams_cli/connection_specs.py
yams_cli/profile.py
yams_cli/utils.py
yams_cli/logic/__init__.py
yams_cli/logic/args.py
yams_cli/logic/cli.py
yams_cli/logic/dispatcher.py
yams_cli/logic/injection.py
yams_cli/logic/core/__init__.py
yams_cli/logic/core/http_client.py
yams_cli/logic/core/manager.py
yams_cli/logic/core/models.py
yams_cli/logic/exceptions/YamsException.py
yams_cli/logic/exceptions/__init__.py
yams_cli-3.3.9.dist-info/METADATA
yams_cli-3.3.9.dist-info/WHEEL
yams_cli-3.3.9.dist-info/entry_points.txt
yams_cli-3.3.9.dist-info/top_level.txt
yams_cli-3.3.9.dist-info/RECORD
