Metadata-Version: 2.1
Name: yams-cli
Version: 3.3.9
Summary: Yams CLI 
Author: Team Edge
Author-email: infrastructure-platform-edge@adevinta.com
Classifier: Programming Language :: Python :: 3.7
Requires-Dist: requests (==2.31.0)
Requires-Dist: configparser (==5.3.0)
Requires-Dist: cryptography (>=39.0.1)
Requires-Dist: docopt (==0.6.2)
Requires-Dist: injector (==0.21.0)
Requires-Dist: pycryptodome (==3.18.0)
Requires-Dist: python-jose (==3.3.0)
Requires-Dist: ecdsa (==0.18)
Requires-Dist: python-dateutil (==2.8.2)
Requires-Dist: pytz
Requires-Dist: cmarkgfm
Requires-Dist: tqdm
